main/__init__.py
main/ls.py
wechat_auto_ls-1.0.data/scripts/ls.py
wechat_auto_ls-1.0.dist-info/LICENSE
wechat_auto_ls-1.0.dist-info/METADATA
wechat_auto_ls-1.0.dist-info/WHEEL
wechat_auto_ls-1.0.dist-info/top_level.txt
wechat_auto_ls-1.0.dist-info/RECORD
