Metadata-Version: 2.1
Name: wechat-auto-ls
Version: 1.0
Summary: 微信自动发送消息脚本
Home-page: https://github.com/HiNoName/wechat_auto
Author: shuai_li
Author-email: 1216710774@qq.com
License: Apache License 2.0
Keywords: wechat
Classifier: Development Status :: 5 - Production/Stable
Classifier: License :: OSI Approved :: Apache Software License
Classifier: Operating System :: OS Independent
Classifier: Programming Language :: Python :: 3
Classifier: Programming Language :: Python :: 3.6
Classifier: Programming Language :: Python :: 3.7
Classifier: Programming Language :: Python :: 3.8
Classifier: Programming Language :: Python :: 3.9
Requires-Python: >=3.8
License-File: LICENSE
Requires-Dist: pywin32 (>=302)
Requires-Dist: uiautomation (>=2.0.18)
